{
  "pages": [
    {
      "locale": "de-CH",
      "medien": "Medien",
      "verein": "Verein",
      "informationen": "Informationen",
      "medienmitteilungen": "Medienmitteilungen"
    },
    {
      "locale": "fr-CH",
      "medien": "Médias",
      "verein": "Association",
      "informationen": "Informations",
      "medienmitteilungen": "Communiqués de presse"
    },
    {
      "locale": "it-CH",
      "medien": "Media",
      "verein": "Associazione",
      "informationen": "Informazioni",
      "medienmitteilungen": "Comunicati stampa"
    }
  ],
  "links": [
    {
      "locale": "de-CH",
      "medien": "/medien",
      "verein": "/verein",
      "informationen": "/informationen",
      "medienmitteilungen": "/medien/medienmitteilungen/"
    },
    {
      "locale": "fr-CH",
      "medien": "/medien",
      "verein": "/verein",
      "informationen": "/informationen",
      "medienmitteilungen": "/medien/medienmitteilungen/"
    },
    {
      "locale": "it-CH",
      "medien": "/medien",
      "verein": "/verein",
      "informationen": "/informationen",
      "medienmitteilungen": "/medien/medienmitteilungen/"
    }
  ]
}
